mediallm_mcp/__about__.py
mediallm_mcp/__init__.py
mediallm_mcp/__main__.py
mediallm_mcp-0.0.3.dist-info/METADATA
mediallm_mcp-0.0.3.dist-info/WHEEL
mediallm_mcp-0.0.3.dist-info/entry_points.txt
mediallm_mcp-0.0.3.dist-info/RECORD
