Metadata-Version: 2.4
Name: mediallm-mcp
Version: 0.0.3
Summary: MCP Server for MediaLLM
Project-URL: Homepage, https://github.com/iamarunbrahma/mediallm
Project-URL: Repository, https://github.com/iamarunbrahma/mediallm
Author-email: Arun Brahma <mithubrahma94@gmail.com>
Maintainer-email: Arun Brahma <mithubrahma94@gmail.com>
Keywords: agent,ai,anthropic,claude,ffmpeg,llm,mcp,media-processing,model-context-protocol,natural-language,ollama,server,tools,video
Requires-Python: >=3.10
Requires-Dist: fastmcp>=2.0.0
Requires-Dist: mcp>=1.0.0
Requires-Dist: mediallm
Requires-Dist: starlette>=0.27.0
Requires-Dist: uvicorn>=0.23.0
Provides-Extra: dev
Requires-Dist: black>=23.0.0; extra == 'dev'
Requires-Dist: ruff>=0.1.0; extra == 'dev'
